geode_hybridmesh/Geode-HybridMesh_brep.dll
geode_hybridmesh/__init__.py
geode_hybridmesh/brep.py
Geode_HybridMesh-1.0.0.dist-info/METADATA
Geode_HybridMesh-1.0.0.dist-info/WHEEL
Geode_HybridMesh-1.0.0.dist-info/top_level.txt
Geode_HybridMesh-1.0.0.dist-info/RECORD
