Metadata-Version: 2.1
Name: Geode-HybridMesh
Version: 1.0.0
Summary: Template for creating your own OpenGeode private module
Home-page: https://github.com/Geode-solutions/Geode-ModuleTemplate
Author: Geode-solutions
Author-email: contact@geode-solutions.com
License: Proprietary
Platform: UNKNOWN
Requires-Dist: OpenGeode-core (==12.*,>=12.3.4)
Requires-Dist: Geode-Common (==23.*,>=23.1.25)
Requires-Dist: Geode-Parameterization (==1.*,>=1.15.2)
Requires-Dist: Geode-SimplexRemesh (==5.*,>=5.1.8)
